gestao_consumo-0.1.2.dist-info/licenses/LICENSE
gestaodeconsumo/__init__.py
gestaodeconsumo/main.py
gestao_consumo-0.1.2.dist-info/METADATA
gestao_consumo-0.1.2.dist-info/WHEEL
gestao_consumo-0.1.2.dist-info/entry_points.txt
gestao_consumo-0.1.2.dist-info/top_level.txt
gestao_consumo-0.1.2.dist-info/RECORD
