Metadata-Version: 2.4
Name: gestao-consumo
Version: 0.1.2
Summary: Sistema de gestão de consumo residencial de água, energia e gás
Author-email: "David Duarte, Danilson Gonçalves, Rafael Fortes e Wilker Lopes" <grupo3@exemplo.com>
License: MIT
Requires-Python: >=3.6
License-File: LICENSE
Requires-Dist: pandas
Requires-Dist: tabulate
Dynamic: license-file
